Metadata-Version: 2.1
Name: AuthMe
Version: 0.1.5
Summary: A python authentication package to work with postgresql, inspired from devise gem for ruby.
Author: Soumit Das
Author-email: its.soumit.das@gmail.com
Classifier: Programming Language :: Python :: 3
Classifier: Operating System :: OS Independent
Requires-Dist: PyJWT
Requires-Dist: psycopg2
